kenall/__init__.py
kenall/base_row.py
kenall/parser.py
kenall/row.py
kenall/util.py
kenall-0.0.1.dist-info/LICENSE
kenall-0.0.1.dist-info/WHEEL
kenall-0.0.1.dist-info/METADATA
kenall-0.0.1.dist-info/RECORD
